katakasar_machine/__init__.py
katakasar_machine/abusiveness_detector.py
katakasar_machine/model.pkl
katakasar_machine/tfidf_vectorizer.pkl
katakasar_machine-0.8.dist-info/METADATA
katakasar_machine-0.8.dist-info/WHEEL
katakasar_machine-0.8.dist-info/top_level.txt
katakasar_machine-0.8.dist-info/RECORD
