Metadata-Version: 2.1
Name: katakasar-machine
Version: 0.8
Requires-Dist: scikit-learn
Requires-Dist: pandas
Requires-Dist: nltk
